tests/__init__.py
tests/helpers.py
tests/test_timer.py
timemarker/__init__.py
timemarker/timer.py
timemarker-0.2.0.dist-info/DESCRIPTION.rst
timemarker-0.2.0.dist-info/METADATA
timemarker-0.2.0.dist-info/RECORD
timemarker-0.2.0.dist-info/WHEEL
timemarker-0.2.0.dist-info/metadata.json
timemarker-0.2.0.dist-info/top_level.txt
